eth_transfer/__init__.py
eth_transfer/gas.py
eth_transfer/main.py
eth_transfer/transaction.py
eth_transfer-0.0.3.dist-info/METADATA
eth_transfer-0.0.3.dist-info/WHEEL
eth_transfer-0.0.3.dist-info/licenses/LICENSE
eth_transfer-0.0.3.dist-info/RECORD
