Metadata-Version: 2.1
Name: eth_transfer
Version: 0.0.3
Summary: Easily send transactions on the Ethereum blockchain and fine tune gas parameters
Project-URL: Homepage, https://github.com/MidpriceDog/eth_transfer
Project-URL: Bug Tracker, https://github.com/MidpriceDog/eth_transfer/issues
Author: MidpriceDog
License: MIT License
License-File: LICENSE
Keywords: blockchain,eth,ether,ethereum,wallet
Classifier: Development Status :: 2 - Pre-Alpha
Classifier: Intended Audience :: Developers
Classifier: Operating System :: OS Independent
Classifier: Programming Language :: Python :: 3.7
Classifier: Programming Language :: Python :: 3.8
Classifier: Programming Language :: Python :: 3.9
Classifier: Programming Language :: Python :: 3.10
Requires-Python: >=3.7.*
Requires-Dist: matplotlib>=3.5.3
Requires-Dist: numpy>=1.23.2
Requires-Dist: pandas>=1.4.4
Requires-Dist: python-dotenv>=0.20.0
Requires-Dist: requests>=2.28.1
Requires-Dist: web3>=5.31.1
Requires-Dist: websockets>=9.1
